vnpy_baostock
