Metadata-Version: 2.1
Name: vnpy-baostock
Version: 1.0.1
Summary: BaoStock datafeed for vn.py quant trading framework.
Home-page: https://github.com/flytrap/vnpy_baostock
Author: flytap
Author-email: hiddenstat@gmail.com
License: MIT
Keywords: baostock,quant,quantitative,investment,trading,algotrading
Platform: UNKNOWN
Classifier: Development Status :: 5 - Production/Stable
Classifier: Operating System :: OS Independent
Classifier: Programming Language :: Python :: 3
Classifier: Programming Language :: Python :: 3.7
Classifier: Topic :: Office/Business :: Financial :: Investment
Classifier: Programming Language :: Python :: Implementation :: CPython
Classifier: License :: OSI Approved :: MIT License
Classifier: Natural Language :: Chinese (Simplified)
License-File: LICENSE
